icd10/__init__.py
icd10/chapter_block.py
icd10/data/byomei_id2disease.json.gz
icd10/data/icd_code2byomei_ids_or_icd_codes.json.gz
icd10/data/icd_code2category.json.gz
icd10/data/index_word2icd.json.gz
icd10/icd.py
icd10/util.py
ja_icd10-0.1.2.post20210701.dist-info/WHEEL
ja_icd10-0.1.2.post20210701.dist-info/METADATA
ja_icd10-0.1.2.post20210701.dist-info/RECORD
