Metadata-Version: 2.1
Name: ja-icd10
Version: 0.1.2.post20210701
Summary: ICD-10 国際疾病分類の日本語情報を扱うためのパッケージ
Author: Yuki Okuda
Author-email: y.okuda@dr-ubie.com
Requires-Python: >=3.8,<4.0
Classifier: Programming Language :: Python :: 3
Classifier: Programming Language :: Python :: 3.8
Classifier: Programming Language :: Python :: 3.9
Requires-Dist: pandas (>=1.3.0,<2.0.0)
